openpmd_api-0.16.1.post1.dist-info/RECORD
openpmd_api-0.16.1.post1.dist-info/entry_points.txt
openpmd_api-0.16.1.post1.dist-info/WHEEL
openpmd_api-0.16.1.post1.dist-info/METADATA
openpmd_api-0.16.1.post1.dist-info/top_level.txt
openpmd_api-0.16.1.post1.dist-info/licenses/COPYING.LESSER
openpmd_api-0.16.1.post1.dist-info/licenses/COPYING
openpmd_api/DaskArray.py
openpmd_api/DataFrame.py
openpmd_api/openpmd_api_cxx.cpython-310-i386-linux-gnu.so
openpmd_api/DaskDataFrame.py
openpmd_api/__init__.py
openpmd_api/pipe/__main__.py
openpmd_api/pipe/__init__.py
openpmd_api/ls/__main__.py
openpmd_api/ls/__init__.py
openpmd_api.libs/libstdc++-d2a021ba.so.6.0.32
openpmd_api.libs/libgcc_s-f3fb5a36.so.1
