Metadata-Version: 2.1
Name: openPMD-api
Version: 0.16.1.post1
Summary: C++ & Python API for Scientific I/O with openPMD
Home-page: https://www.openPMD.org
Author: Axel Huebl, Franz Poeschel, Fabian Koller, Junmin Gu
Author-email: axelhuebl@lbl.gov, f.poeschel@hzdr.de
Maintainer: Axel Huebl
Maintainer-email: axelhuebl@lbl.gov
Project-URL: Documentation, https://openpmd-api.readthedocs.io
Project-URL: Doxygen, https://www.openpmd.org/openPMD-api
Project-URL: Reference, https://doi.org/10.14278/rodare.27
Project-URL: Source, https://github.com/openPMD/openPMD-api
Project-URL: Tracker, https://github.com/openPMD/openPMD-api/issues
Keywords: openPMD openscience hdf5 adios mpi hpc research file-format file-handling
Classifier: Development Status :: 4 - Beta
Classifier: Natural Language :: English
Classifier: Environment :: Console
Classifier: Intended Audience :: Science/Research
Classifier: Operating System :: OS Independent
Classifier: Topic :: Scientific/Engineering
Classifier: Topic :: Database :: Front-Ends
Classifier: Programming Language :: C++
Classifier: Programming Language :: Python :: 3
Classifier: Programming Language :: Python :: 3.8
Classifier: Programming Language :: Python :: 3.9
Classifier: Programming Language :: Python :: 3.10
Classifier: Programming Language :: Python :: 3.11
Classifier: Programming Language :: Python :: 3.12
Classifier: Programming Language :: Python :: 3.13
Classifier: License :: OSI Approved :: GNU Lesser General Public License v3 or later (LGPLv3+)
Requires-Python: >=3.8
License-File: COPYING
License-File: COPYING.LESSER
Requires-Dist: numpy>=1.15.0
